niconico.py
setup.py
nico_tools/__init__.py
nico_tools/convunichrs.py
nico_tools/mp3_tag.py
nico_tools/mylist.py
nico_tools/mylist_items.py
nico_tools/nico_xml_parser.py
nico_tools/nicovideo_dl.py
nico_tools/nicowalker.py
nico_tools/web_drivers.json
nico_tools/web_drivers.py
pyniconico.egg-info/PKG-INFO
pyniconico.egg-info/SOURCES.txt
pyniconico.egg-info/dependency_links.txt
pyniconico.egg-info/entry_points.txt
pyniconico.egg-info/requires.txt
pyniconico.egg-info/top_level.txt