Metadata-Version: 1.0
Name: pyniconico
Version: 1.4
Summary: Python NicoNico Douga downloader
Home-page: https://github.com/Sakaki/pyniconico
Author: Sakaki Mirai
Author-email: sakaki333@gmail.com
License: Written in ./LICENSE for this project. But please be careful this project download external programs.
Platform: UNKNOWN
